{"loadMethods":{},"label":"BNB Transfer","name":"BNBTransfer","icon":"https://raw.githubusercontent.com/Outerbridgeio/Outerbridge/master/packages/components/nodes/BNBTransfer/bnb.svg","type":"action","category":"Cryptocurrency","version":1,"description":"Send/Transfer BNB to an address","incoming":1,"outgoing":1,"networks":[{"label":"Network","name":"network","type":"options","options":[{"label":"Binance Smart Chain Mainnet","name":"bsc","parentGroup":"Binance Smart Chain"},{"label":"Binance Smart Chain Testnet","name":"bsc-testnet","parentGroup":"Binance Smart Chain"}]},{"label":"Network Provider","name":"networkProvider","type":"asyncOptions","loadMethod":"getNetworkProviders"},{"label":"RPC Endpoint","name":"jsonRPC","type":"string","default":"","show":{"networks.networkProvider":["customRPC"]}},{"label":"Websocket Endpoint","name":"websocketRPC","type":"string","default":"","show":{"networks.networkProvider":["customWebsocket"]}}],"credentials":[{"label":"Credential Method","name":"credentialMethod","type":"options","options":[{"label":"Alchemy API Key","name":"alchemyApi","show":{"networks.networkProvider":["alchemy"]}},{"label":"Infura API Key","name":"infuraApi","show":{"networks.networkProvider":["infura"]}},{"label":"QuickNode Endpoints","name":"quickNodeEndpoints","show":{"networks.networkProvider":["quicknode"]}}],"show":{"networks.networkProvider":["alchemy","infura","quicknode"]}}],"inputParameters":[{"label":"Wallet To Transfer","name":"wallet","type":"asyncOptions","description":"Wallet account to send/transfer BNB","loadFromDbCollections":["Wallet"],"loadMethod":"getWallets"},{"label":"Address To Receive","name":"address","type":"string","default":"","description":"Address to receive BNB"},{"label":"Amount","name":"amount","type":"number","description":"Amount of BNB to transfer"},{"label":"Gas Limit","name":"gasLimit","type":"number","optional":true,"placeholder":"100000","description":"Maximum price you are willing to pay when sending a transaction"},{"label":"Max Fee per Gas","name":"maxFeePerGas","type":"number","optional":true,"placeholder":"200","description":"The maximum price (in wei) per unit of gas for transaction. See <a target=\"_blank\" href=\"https://docs.alchemy.com/docs/maxpriorityfeepergas-vs-maxfeepergas\">more</a>"},{"label":"Max Priority Fee per Gas","name":"maxPriorityFeePerGas","type":"number","optional":true,"placeholder":"5","description":"The priority fee price (in wei) per unit of gas for transaction. See <a target=\"_blank\" href=\"https://docs.alchemy.com/docs/maxpriorityfeepergas-vs-maxfeepergas\">more</a>"}],"filePath":"https://raw.githubusercontent.com/fruitbox12/nodes/main/nodes/BNBTransfer/BNBTransfer.js"}
